{
 "custom_fields": [], 
 "custom_perms": [], 
 "doctype": "Expense Claim Account", 
 "property_setters": [
  {
   "_assign": null, 
   "_comments": null, 
   "_liked_by": null, 
   "_user_tags": null, 
   "creation": "2018-06-06 15:07:57.955577", 
   "default_value": null, 
   "doc_type": "Expense Claim Account", 
   "docstatus": 0, 
   "doctype_or_field": "DocField", 
   "field_name": "default_account", 
   "idx": 0, 
   "modified": "2018-06-06 15:07:57.955577", 
   "modified_by": "sethusrinivasan.s@voltechgroup.com", 
   "name": "Expense Claim Account-default_account-width", 
   "owner": "sethusrinivasan.s@voltechgroup.com", 
   "parent": null, 
   "parentfield": null, 
   "parenttype": null, 
   "property": "width", 
   "property_type": null, 
   "value": "390"
  }
 ], 
 "sync_on_migrate": 1
}